pythonish_ql/__init__.py
pythonish_ql/_version.py
pythonish_ql/pythonish_ql.py
pythonish_ql-0.0.7.dist-info/LICENSE
pythonish_ql-0.0.7.dist-info/METADATA
pythonish_ql-0.0.7.dist-info/WHEEL
pythonish_ql-0.0.7.dist-info/top_level.txt
pythonish_ql-0.0.7.dist-info/RECORD
