Metadata-Version: 2.1
Name: pythonish-ql
Version: 0.0.7
Summary: Pythonish query language for dictionary-like data
Home-page: https://github.com/dsblank/pythonish-ql
Author: Doug Blank
License: MIT License
Platform: Linux
Platform: Mac OS X
Platform: Windows
Classifier: License :: OSI Approved :: MIT License
Classifier: Programming Language :: Python
Classifier: Programming Language :: Python :: 3
Classifier: Programming Language :: Python :: 3.8
Classifier: Programming Language :: Python :: 3.9
Classifier: Programming Language :: Python :: 3.10
Requires-Python: >=3.8
License-File: LICENSE
Requires-Dist: gramps
